huaweicloudsdkcoc/__init__.py
huaweicloudsdkcoc/v1/__init__.py
huaweicloudsdkcoc/v1/coc_async_client.py
huaweicloudsdkcoc/v1/coc_client.py
huaweicloudsdkcoc/v1/model/__init__.py
huaweicloudsdkcoc/v1/model/accept_script_request.py
huaweicloudsdkcoc/v1/model/accept_script_response.py
huaweicloudsdkcoc/v1/model/account_base_response.py
huaweicloudsdkcoc/v1/model/account_change_pwd_plan.py
huaweicloudsdkcoc/v1/model/add_script_model.py
huaweicloudsdkcoc/v1/model/alarm_handle_history.py
huaweicloudsdkcoc/v1/model/alarm_info_dto.py
huaweicloudsdkcoc/v1/model/alarm_schedule_instance.py
huaweicloudsdkcoc/v1/model/alarm_to_incident_request_body.py
huaweicloudsdkcoc/v1/model/application_create_request.py
huaweicloudsdkcoc/v1/model/application_update_request.py
huaweicloudsdkcoc/v1/model/application_view_query_response_data.py
huaweicloudsdkcoc/v1/model/approval_job_script_model.py
huaweicloudsdkcoc/v1/model/atomic_input_model.py
huaweicloudsdkcoc/v1/model/atomic_model.py
huaweicloudsdkcoc/v1/model/atomic_output_model.py
huaweicloudsdkcoc/v1/model/authorizable_ticket_body.py
huaweicloudsdkcoc/v1/model/authorize_ticket_common_info.py
huaweicloudsdkcoc/v1/model/authorize_ticket_info.py
huaweicloudsdkcoc/v1/model/auto_handler_alarm_request_body.py
huaweicloudsdkcoc/v1/model/base_id_response_data.py
huaweicloudsdkcoc/v1/model/base_query_assess_task_list_response_data.py
huaweicloudsdkcoc/v1/model/base_response.py
huaweicloudsdkcoc/v1/model/basic_dto.py
huaweicloudsdkcoc/v1/model/basic_resource_tag_response_data.py
huaweicloudsdkcoc/v1/model/basic_response.py
huaweicloudsdkcoc/v1/model/batch_create_application_view_request.py
huaweicloudsdkcoc/v1/model/batch_create_application_view_request_body.py
huaweicloudsdkcoc/v1/model/batch_create_application_view_request_body_application_list.py
huaweicloudsdkcoc/v1/model/batch_create_application_view_request_body_component_list.py
huaweicloudsdkcoc/v1/model/batch_create_application_view_request_body_group_list.py
huaweicloudsdkcoc-3.1.184.dist-info/METADATA
huaweicloudsdkcoc-3.1.184.dist-info/WHEEL
huaweicloudsdkcoc-3.1.184.dist-info/licenses/LICENSE
huaweicloudsdkcoc-3.1.184.dist-info/RECORD
